jfsd/__init__.py
jfsd/__main__.py
jfsd/_version.py
jfsd/applied_forces.py
jfsd/config.py
jfsd/ewald_tables.py
jfsd/interactive.py
jfsd/jaxmd_space.py
jfsd/jaxmd_util.py
jfsd/jfsd_gui.py
jfsd/lanczos.py
jfsd/main.py
jfsd/mobility.py
jfsd/resistance.py
jfsd/shear.py
jfsd/solver.py
jfsd/thermal.py
jfsd/utils.py
jfsd-0.2.2.dist-info/licenses/LICENSE
jfsd-0.2.2.dist-info/licenses/LICENSE_SHORT
jfsd-0.2.2.dist-info/METADATA
jfsd-0.2.2.dist-info/WHEEL
jfsd-0.2.2.dist-info/entry_points.txt
jfsd-0.2.2.dist-info/top_level.txt
jfsd-0.2.2.dist-info/RECORD
