Metadata-Version: 2.4
Name: jfsd
Version: 0.2.2
Summary: Python implementation of Fast Stokesian Dynamics methods.
Author-email: William Torre <william.torre.ct@gmail.com>
License: 
Project-URL: GitHub, https://github.com/torrewk/Python-Jax-Fast-Stokesian-Dynamics
Project-URL: documentation, https://github.com/torrewk/Python-Jax-Fast-Stokesian-Dynamics
Keywords: irods,data management,storage
Classifier: Programming Language :: Python :: 3
Classifier: Programming Language :: Python :: 3.9
Classifier: Programming Language :: Python :: 3.10
Classifier: Programming Language :: Python :: 3.11
Classifier: Development Status :: 3 - Alpha
Classifier: License :: OSI Approved :: MIT License
Requires-Python: >=3.9
License-File: LICENSE
License-File: LICENSE_SHORT
Requires-Dist: jax==0.4.17
Requires-Dist: numpy
Requires-Dist: scipy==1.10.1
Requires-Dist: jraph==0.0.6.dev0
Requires-Dist: absl-py==2.1.0
Requires-Dist: tomli; python_version < "3.11"
Requires-Dist: tqdm
Requires-Dist: PySide6
Requires-Dist: vispy
Requires-Dist: toml
Provides-Extra: test
Requires-Dist: pylint; extra == "test"
Requires-Dist: pytest; extra == "test"
Requires-Dist: freud-analysis; extra == "test"
Requires-Dist: ruff; extra == "test"
Requires-Dist: mypy; extra == "test"
Requires-Dist: types-tqdm; extra == "test"
Requires-Dist: sphinx; extra == "test"
Requires-Dist: sphinx-rtd-theme; extra == "test"
Requires-Dist: sphinxcontrib-napoleon; extra == "test"
Requires-Dist: sphinx-autodoc-typehints; extra == "test"
Requires-Dist: sphinx_inline_tabs; extra == "test"
Requires-Dist: sphinx_copybutton; extra == "test"
Dynamic: license-file
